{
    "Success": true,
    "Message": null,
    "Data": {
        "Results": [
            {
                "FloorplanId": "53",
                "Stocknumber": 2454,
                "ProcessedDate": "12/13/2403",
                "UnitMake": "Honda",
                "UnitModel": "Civic",
                "UnitYear": "2004",
                "DaysOnFloor": "43"
            },
            {
                "FloorplanId": "53",
                "Stocknumber": 2454,
                "ProcessedDate": "12/13/2403",
                "UnitMake": "Honda",
                "UnitModel": "Civic",
                "UnitYear": "2004",
                "DaysOnFloor": "43"
            },
            {
                "FloorplanId": "53",
                "Stocknumber": 2454,
                "ProcessedDate": "12/13/2403",
                "UnitMake": "Honda",
                "UnitModel": "Civic",
                "UnitYear": "2004",
                "DaysOnFloor": "43"
            }
        ]
    }
}
